{
  "JSCA": {
    "A": 100,
    "C": 290,
    "P": 291,
    "N": 292,
    "R": 500,
    "OK": 505,
    "OC": 510,
    "M": 702,
    "O": 705,
    "PC": 900,
    "PP": 901,
    "BC": 902,
    "MA": 920,
    "ZC": 930,
    "EC": 935,
    "V": 940
  },
  "STANLEY_GIBBONS": {
    "FR": 95,
    "Z": 96,
    "-": 100,
    "MS": 100,
    "G": 100,
    "H": 200,
    "E": 205,
    "K": 210,
    "U": 215,
    "G": 220,
    "ED": 225,
    "M": 230,
    "N": 235,
    "SB": 240,
    "R": 245,
    "S": 250,
    "B": 255,
    "D": 300,
    "J": 300,
    "JD": 305,
    "MD": 310,
    "V": 315,
    "O": 350,
    "OB": 355,
    "OS": 360,
    "P": 365,
    "L": 370,
    "T": 375,
    "TD": 380,
    "Z":  385,
    "ZA": 386,
    "F":  390,
    "FE": 392,
    "FEG": 393,
    "FG":  394,
    "FSC": 396,
    "FPS": 397,
    "FX": 398,
    "FWM": 399,
    "C":  440,
    "CB": 450,
    "CE": 455,
    "CO": 460,
    "CQ": 465,
    "MC": 470,
    "GY": 475,
    "EB": 480,
    "EO": 485,
    "IS": 500,
    "A":  700,
    "MR": 702,
    "OL": 704,
    "OY": 706,
    "QB": 708,
    "MQ": 710,
    "QY": 712,
    "QE": 714,
    "AR": 730,
    "LC B": 750,
    "LMS": 760
  },
  "SCOTT": {
    "B": 250,
    "C":  290,
    "CB": 295,
    "CE": 323,
    "CO": 356,
    "R": 296,
    "S": 298,
    "D": 300,
    "J": 300,
    "E": 320,
    "F": 340,
    "O": 350,
    "OY": 355,
    "L": 370,
    "I": 701,
    "M": 702,
    "MC": 702,
    "MR": 702,
    "MQ": 704,
    "OL": 704,
    "N": 710,
    "RA": 716,
    "RAB": 718,
    "RAC": 720,
    "RAJ": 722,
    "SMH": 726,
    "Q": 730,
    "P": 740,
    "NJ": 750,
    "NB": 755,
    "WMMH": 770,
    "NIMH": 757
  },
  "MICHEL": {
    "V Zd": 90,
    "Z": 100,
    "GER": 100,
    "A": 100,
    "Block": 120,
    "H-Blatt": 125,
    "HB": 125,
    "I A": 130,
    "I B": 130,
    "II": 131,
    "II A": 131,
    "II B": 131,
    "III": 132,
    "III A": 132,
    "III B": 132,
    "IV A": 133,
    "IV B": 133,
    "V A": 134,
    "V B": 134,
    "VI A": 135,
    "VI B": 135,
    "VII": 136,
    "IX": 138,
    "K": 150,
    "KZ": 151,
    "RL": 152,
    "S": 153,
    "SK": 154,
    "W": 155,
    "WZ": 156,
    "O": 350,
    "D": 350,
    "EG": 370,
    "T": 405,
    "HF-": 450,
    "HF": 450,
    "J": 500,
    "LC A": 510,
    "LC B": 515,
    "LC C": 520
  }
}